pif/__init__.py
pif/exceptions.py
pif/providers/__init__.py
pif/providers/blank.py
pif/providers/existing_singleton.py
pif/providers/factory.py
pif/providers/provider.py
pif/providers/singleton.py
pif/providers/util.py
pif/wiring.py
python_injection_framework-0.0.2.dist-info/LICENSE
python_injection_framework-0.0.2.dist-info/METADATA
python_injection_framework-0.0.2.dist-info/WHEEL
python_injection_framework-0.0.2.dist-info/RECORD
