Metadata-Version: 2.1
Name: python-injection-framework
Version: 0.0.2
Summary: Another Python Dependency injector framework.
License: BSD-3
Author: Zac Scott
Author-email: zac.scott11@gmail.com
Requires-Python: >=3.10,<4.0
Classifier: License :: Other/Proprietary License
Classifier: Programming Language :: Python :: 3
Classifier: Programming Language :: Python :: 3.10
Classifier: Programming Language :: Python :: 3.11
Classifier: Programming Language :: Python :: 3.12
